mtflib.libs/libstdc++-496613c0.so.6.0.32
mtflib.libs/libgcc_s-a3a07607.so.1
mtflib.libs/libgomp-1f0f45f5.so.1.0.0
mtflib-1.5.2.dist-info/WHEEL
mtflib-1.5.2.dist-info/top_level.txt
mtflib-1.5.2.dist-info/METADATA
mtflib-1.5.2.dist-info/RECORD
mtflib-1.5.2.dist-info/licenses/LICENSE
mtflib/taylor_map.py
mtflib/taylor_function.py
mtflib/elementary_coefficients.py
mtflib/backend.py
mtflib/elementary_functions.py
mtflib/complex_taylor_function.py
mtflib/py.typed
mtflib/__init__.py
mtflib/backends/cpp/mtf_cpp.cpython-310-x86_64-linux-gnu.so
mtflib/backends/cpp/precomputed_coefficients.hpp
mtflib/backends/cpp/mtf_data.hpp
mtflib/backends/cpp/mtf_data.cpp
mtflib/backends/cpp/pybind_wrapper.cpp
mtflib/backends/c/c_pybind_wrapper.cpp
mtflib/backends/c/c_backend.cpp
mtflib/backends/c/c_backend.h
mtflib/backends/c/mtf_c_backend.cpython-310-x86_64-linux-gnu.so
