Metadata-Version: 2.4
Name: mtflib
Version: 1.5.2
Summary: A library for working with Multivariate Taylor Functions.
Author-email: Shashikant Manikonda <manikonda@outlook.com>
License: MIT License
Project-URL: Homepage, https://github.com/shashi-manikonda/MTFLibrary
Project-URL: Bug Tracker, https://github.com/shashi-manikonda/MTFLibrary/issues
Classifier: Development Status :: 4 - Beta
Classifier: Intended Audience :: Developers
Classifier: Intended Audience :: Science/Research
Classifier: Programming Language :: Python :: 3
Classifier: Programming Language :: C++
Classifier: Topic :: Scientific/Engineering :: Mathematics
Classifier: Topic :: Software Development :: Libraries
Requires-Python: >=3.8
License-File: LICENSE
Requires-Dist: numpy
Requires-Dist: pandas
Requires-Dist: jupytext
Provides-Extra: torch
Requires-Dist: torch; extra == "torch"
Provides-Extra: test
Requires-Dist: pytest; extra == "test"
Requires-Dist: matplotlib; extra == "test"
Requires-Dist: nbconvert; extra == "test"
Requires-Dist: ipykernel; extra == "test"
Requires-Dist: jupytext; extra == "test"
Requires-Dist: pandas; extra == "test"
Requires-Dist: torch; extra == "test"
Requires-Dist: ipython; extra == "test"
Requires-Dist: sympy; extra == "test"
Requires-Dist: jupyter; extra == "test"
Provides-Extra: docs
Requires-Dist: sphinx; extra == "docs"
Requires-Dist: sphinx-rtd-theme; extra == "docs"
Requires-Dist: myst_parser; extra == "docs"
Requires-Dist: sympy; extra == "docs"
Requires-Dist: matplotlib; extra == "docs"
Requires-Dist: pandas; extra == "docs"
Requires-Dist: torch; extra == "docs"
Requires-Dist: ipython; extra == "docs"
Requires-Dist: nbconvert; extra == "docs"
Provides-Extra: dev
Requires-Dist: pytest; extra == "dev"
Requires-Dist: matplotlib; extra == "dev"
Requires-Dist: nbconvert; extra == "dev"
Requires-Dist: ipykernel; extra == "dev"
Requires-Dist: torch; extra == "dev"
Requires-Dist: sphinx; extra == "dev"
Requires-Dist: sphinx-rtd-theme; extra == "dev"
Requires-Dist: myst_parser; extra == "dev"
Requires-Dist: sympy; extra == "dev"
Requires-Dist: pre-commit; extra == "dev"
Requires-Dist: ruff; extra == "dev"
Requires-Dist: jupytext; extra == "dev"
Requires-Dist: pandas; extra == "dev"
Requires-Dist: ipython; extra == "dev"
Requires-Dist: mypy; extra == "dev"
Dynamic: license-file
